timesleuth/__init__.py
timesleuth/anomaly_detection.py
timesleuth/core.py
timesleuth/reporting.py
timesleuth/timeline.py
timesleuth/utils.py
timesleuth-1.0.0.dist-info/licenses/LICENSE
timesleuth-1.0.0.dist-info/METADATA
timesleuth-1.0.0.dist-info/WHEEL
timesleuth-1.0.0.dist-info/top_level.txt
timesleuth-1.0.0.dist-info/RECORD
