Metadata-Version: 2.4
Name: timesleuth
Version: 1.0.0
Summary: Digital forensics timestamp analysis library for detecting suspicious activity
Home-page: https://github.com/MohammadNazmulDev/TimeSleuth
Author: Mohammad Nazmul
Author-email: mohammadnazmuldev@gmail.com
Project-URL: Bug Reports, https://github.com/MohammadNazmulDev/TimeSleuth/issues
Project-URL: Source Code, https://github.com/MohammadNazmulDev/TimeSleuth
Project-URL: Documentation, https://github.com/MohammadNazmulDev/TimeSleuth#readme
Keywords: forensics digital-forensics timestamp security incident-response malware-analysis cybersecurity
Classifier: Development Status :: 5 - Production/Stable
Classifier: Intended Audience :: Information Technology
Classifier: Intended Audience :: Legal Industry
Classifier: Intended Audience :: System Administrators
Classifier: Topic :: Security
Classifier: Topic :: System :: Filesystems
Classifier: Topic :: Software Development :: Libraries :: Python Modules
Classifier: License :: OSI Approved :: MIT License
Classifier: Programming Language :: Python :: 3
Classifier: Programming Language :: Python :: 3.7
Classifier: Programming Language :: Python :: 3.8
Classifier: Programming Language :: Python :: 3.9
Classifier: Programming Language :: Python :: 3.10
Classifier: Programming Language :: Python :: 3.11
Classifier: Programming Language :: Python :: 3.12
Classifier: Operating System :: OS Independent
Requires-Python: >=3.7
License-File: LICENSE
Dynamic: author
Dynamic: author-email
Dynamic: classifier
Dynamic: description
Dynamic: description-content-type
Dynamic: home-page
Dynamic: keywords
Dynamic: license-file
Dynamic: project-url
Dynamic: requires-python
Dynamic: summary
